graphs_amarsh/__init__.py
graphs_amarsh/bfs.py
graphs_amarsh/heapq.py
graphs_amarsh/sp.py
graphs_amarsh-0.0.3.dist-info/METADATA
graphs_amarsh-0.0.3.dist-info/WHEEL
graphs_amarsh-0.0.3.dist-info/RECORD
