Metadata-Version: 2.3
Name: graphs_amarsh
Version: 0.0.3
Summary: A small program that solves Dijkstra's shortest path problem
Project-URL: Homepage, https://github.com/art3mchik/cs3250hw4artem
Project-URL: Bug Tracker, https://github.com/art3mchik/cs3250hw4artem/issues
Author-email: Artem Marsh <marshartem@gmail.com>
Classifier: License :: OSI Approved :: MIT License
Classifier: Operating System :: OS Independent
Classifier: Programming Language :: Python :: 3
Requires-Python: >=3.7
